dotlink/__init__.py
dotlink/__main__.py
dotlink/__version__.py
dotlink/actions.py
dotlink/cli.py
dotlink/core.py
dotlink/types.py
dotlink/util.py
dotlink/tests/__init__.py
dotlink/tests/actions.py
dotlink/tests/core.py
dotlink/tests/smoke.py
dotlink/tests/types.py
dotlink/tests/util.py
dotlink-2.1.dist-info/entry_points.txt
dotlink-2.1.dist-info/LICENSE
dotlink-2.1.dist-info/WHEEL
dotlink-2.1.dist-info/METADATA
dotlink-2.1.dist-info/RECORD
