Metadata-Version: 2.1
Name: dotlink
Version: 2.1
Summary: Automate deployment of dotfiles to local paths or remote hosts
Author-email: Amethyst Reese <amy@noswap.com>
Requires-Python: >=3.8
Classifier: Development Status :: 5 - Production/Stable
Classifier: License :: OSI Approved :: MIT License
Classifier: Operating System :: OS Independent
Classifier: Topic :: Utilities
Requires-Dist: click >= 8
Requires-Dist: platformdirs >= 4
Requires-Dist: typing_extensions >= 4
Requires-Dist: attribution==1.7.1 ; extra == "dev"
Requires-Dist: black==24.4.2 ; extra == "dev"
Requires-Dist: flake8==7.0.0 ; extra == "dev"
Requires-Dist: flit==3.9.0 ; extra == "dev"
Requires-Dist: mypy==1.10.0 ; extra == "dev"
Requires-Dist: pytest==8.2.0 ; extra == "dev"
Requires-Dist: usort==1.0.8.post1 ; extra == "dev"
Requires-Dist: ufmt==2.5.1 ; extra == "dev"
Project-URL: Github, https://github.com/amyreese/dotlink
Project-URL: home-page, https://github.com/amyreese/dotlink
Provides-Extra: dev
